{
    "description": "",
    "tags": [],
    "size": {
        "height": 1080,
        "width": 1920
    },
    "objects": [
        {
            "id": 580946239,
            "classId": 2737563,
            "description": "",
            "geometryType": "polygon",
            "labelerLogin": "tiruss",
            "createdAt": "2020-11-23T08:29:10.000Z",
            "updatedAt": "2020-12-07T14:40:38.608Z",
            "tags": [],
            "classTitle": "Vehicle_Bus",
            "points": {
                "exterior": [
                    [
                        891,
                        526
                    ],
                    [
                        888,
                        526
                    ],
                    [
                        886,
                        528
                    ],
                    [
                        885,
                        532
                    ],
                    [
                        887,
                        555
                    ],
                    [
                        894,
                        554
                    ],
                    [
                        909,
                        555
                    ],
                    [
                        911,
                        553
                    ],
                    [
                        912,
                        549
                    ],
                    [
                        913,
                        541
                    ],
                    [
                        912,
                        529
                    ],
                    [
                        909,
                        526
                    ],
                    [
                        895,
                        525
                    ]
                ],
                "interior": []
            }
        }
    ]
}