{
    "description": "",
    "tags": [],
    "size": {
        "height": 1080,
        "width": 1920
    },
    "objects": [
        {
            "id": 580946901,
            "classId": 2737563,
            "description": "",
            "geometryType": "polygon",
            "labelerLogin": "tiruss",
            "createdAt": "2020-11-23T08:40:31.000Z",
            "updatedAt": "2020-11-23T08:40:31.000Z",
            "tags": [],
            "classTitle": "Vehicle_Bus",
            "points": {
                "exterior": [
                    [
                        1121,
                        464
                    ],
                    [
                        1117,
                        470
                    ],
                    [
                        1114,
                        472
                    ],
                    [
                        1109,
                        477
                    ],
                    [
                        1098,
                        478
                    ],
                    [
                        1095,
                        478
                    ],
                    [
                        1091,
                        481
                    ],
                    [
                        1087,
                        482
                    ],
                    [
                        1084,
                        482
                    ],
                    [
                        1081,
                        484
                    ],
                    [
                        1077,
                        488
                    ],
                    [
                        1060,
                        511
                    ],
                    [
                        1061,
                        526
                    ],
                    [
                        1064,
                        533
                    ],
                    [
                        1066,
                        570
                    ],
                    [
                        1069,
                        574
                    ],
                    [
                        1070,
                        577
                    ],
                    [
                        1070,
                        583
                    ],
                    [
                        1074,
                        586
                    ],
                    [
                        1080,
                        586
                    ],
                    [
                        1084,
                        585
                    ],
                    [
                        1090,
                        585
                    ],
                    [
                        1094,
                        589
                    ],
                    [
                        1099,
                        596
                    ],
                    [
                        1101,
                        598
                    ],
                    [
                        1105,
                        598
                    ],
                    [
                        1111,
                        593
                    ],
                    [
                        1117,
                        589
                    ],
                    [
                        1119,
                        587
                    ],
                    [
                        1145,
                        588
                    ],
                    [
                        1166,
                        592
                    ],
                    [
                        1175,
                        599
                    ],
                    [
                        1180,
                        600
                    ],
                    [
                        1188,
                        599
                    ],
                    [
                        1194,
                        592
                    ],
                    [
                        1202,
                        586
                    ],
                    [
                        1213,
                        585
                    ],
                    [
                        1216,
                        585
                    ],
                    [
                        1219,
                        580
                    ],
                    [
                        1221,
                        578
                    ],
                    [
                        1217,
                        488
                    ],
                    [
                        1216,
                        482
                    ],
                    [
                        1216,
                        480
                    ],
                    [
                        1214,
                        478
                    ],
                    [
                        1210,
                        466
                    ],
                    [
                        1208,
                        466
                    ],
                    [
                        1205,
                        463
                    ],
                    [
                        1202,
                        462
                    ]
                ],
                "interior": []
            }
        }
    ]
}