<?xml version="1.0" encoding="UTF-8"?>
<annotation>
  <ver>v001_1</ver>
  <folder>2</folder>
  <filename>2_20200731_140619_001260</filename>
  <path>Z:\freespace\IPIS_Freespace_verification\20200731_140619\ann</path>
  <source>
    <database>KATECH_DB</database>
  </source>
  <size>
    <width>1920</width>
    <height>1080</height>
    <depth>3</depth>
  </size>
  <segmented>0</segmented>
  <index_max>1</index_max>
 <polygon>
   <name>FreeSpace</name>
   <pose>Unspecified</pose>
   <truncated>0</truncated>
   <difficult>0</difficult>
   <PolyPt><x>524</x><y>764</y><x>633</x><y>709</y><x>749</x><y>655</y><x>826</x><y>618</y><x>903</x><y>583</y><x>954</x><y>559</y><x>963</x><y>552</y><x>968</x><y>552</y><x>969</x><y>560</y><x>970</x><y>562</y><x>974</x><y>562</y><x>975</x><y>559</y><x>987</x><y>559</y><x>988</x><y>562</y><x>994</x><y>562</y><x>994</x><y>553</y><x>999</x><y>554</y><x>1001</x><y>552</y><x>1001</x><y>550</y><x>1009</x><y>550</y><x>1012</x><y>550</y><x>1011</x><y>551</y><x>1011</x><y>553</y><x>1020</x><y>556</y><x>1034</x><y>558</y><x>1048</x><y>560</y><x>1077</x><y>566</y><x>1116</x><y>571</y><x>1163</x><y>577</y><x>1267</x><y>594</y><x>1378</x><y>614</y><x>1418</x><y>619</y><x>1430</x><y>619</y><x>1463</x><y>623</y><x>1515</x><y>632</y><x>1579</x><y>641</y><x>1671</x><y>655</y><x>1712</x><y>662</y><x>1820</x><y>680</y><x>1878</x><y>692</y><x>1836</x><y>715</y><x>1754</x><y>730</y><x>1681</x><y>738</y><x>1610</x><y>748</y><x>1384</x><y>769</y><x>1188</x><y>781</y><x>977</x><y>783</y><x>779</x><y>780</y><x>701</x><y>782</y><x>609</x><y>774</y><x>557</x><y>769</y>
   </PolyPt>
   <index>1</index>
   <review_code>C_v001</review_code>
 </polygon>
   </PolyPt>
   <index>2</index>
   <review_code>C_v001</review_code>
 </polygon>
</annotation>