<?xml version="1.0" encoding="UTF-8"?>
<annotation>
  <ver>v001_1</ver>
  <folder>2</folder>
  <filename>2_20200731_140619_001050.jpg</filename>
  <path>C:\Users\KATECH-02\Desktop\20201125(TQS김지혜)_4차_성선영\20201125_오은경_4차\20200731_140619\2\</path>
  <source>
    <database>KATECH_DB</database>
  </source>
  <size>
    <width>1920</width>
    <height>1080</height>
    <depth>3</depth>
  </size>
  <segmented>0</segmented>
  <index_max>3</index_max>
  <line>
    <name>Lane_White_Solid</name>
    <pose>Unspecified</pose>
    <truncated>0</truncated>
    <difficult>0</difficult>
    <controlPt>
      <x>683</x>
      <y>776</y>
      <x>854</x>
      <y>624</y>
      <x>882</x>
      <y>599</y>
      <x>900</x>
      <y>580</y>
      <x>904</x>
      <y>566</y>
      <x>902</x>
      <y>554</y>
      <x>902</x>
      <y>547</y>
    </controlPt>
    <index>2</index>
    <review_code>C_v001</review_code>
  </line>
  <line>
    <name>Lane_White_Dash</name>
    <pose>Unspecified</pose>
    <truncated>0</truncated>
    <difficult>0</difficult>
    <controlPt>
      <x>933</x>
      <y>557</y>
      <x>961</x>
      <y>567</y>
      <x>1006</x>
      <y>588</y>
      <x>1078</x>
      <y>629</y>
    </controlPt>
    <index>3</index>
    <review_code>C_v001</review_code>
  </line>
  <line>
    <name>Lane_White_Solid</name>
    <pose>Unspecified</pose>
    <truncated>0</truncated>
    <difficult>0</difficult>
    <controlPt>
      <x>984</x>
      <y>563</y>
      <x>1030</x>
      <y>570</y>
      <x>1093</x>
      <y>583</y>
      <x>1169</x>
      <y>598</y>
      <x>1272</x>
      <y>621</y>
      <x>1551</x>
      <y>686</y>
      <x>1734</x>
      <y>732</y>
    </controlPt>
    <index>4</index>
    <review_code>C_v001</review_code>
  </line>
</annotation>
