<?xml version="1.0" encoding="UTF-8"?>
<annotation>
  <ver>v001_1</ver>
  <folder>2</folder>
  <filename>2_20200731_140619_001650.jpg</filename>
  <path>C:\Users\KATECH-02\Desktop\20201125(TQS김지혜)_4차_성선영\20201125_오은경_4차\20200731_140619\2\</path>
  <source>
    <database>KATECH_DB</database>
  </source>
  <size>
    <width>1920</width>
    <height>1080</height>
    <depth>3</depth>
  </size>
  <segmented>0</segmented>
  <index_max>3</index_max>
  <line>
    <name>Lane_White_Solid</name>
    <pose>Unspecified</pose>
    <truncated>0</truncated>
    <difficult>0</difficult>
    <controlPt>
      <x>595</x>
      <y>773</y>
      <x>767</x>
      <y>669</y>
      <x>833</x>
      <y>631</y>
      <x>913</x>
      <y>589</y>
      <x>962</x>
      <y>567</y>
      <x>986</x>
      <y>559</y>
    </controlPt>
    <index>2</index>
    <review_code>C_v001</review_code>
  </line>
  <line>
    <name>Lane_White_Dash</name>
    <pose>Unspecified</pose>
    <truncated>0</truncated>
    <difficult>0</difficult>
    <controlPt>
      <x>1214</x>
      <y>782</y>
      <x>1128</x>
      <y>699</y>
      <x>1051</x>
      <y>614</y>
      <x>1029</x>
      <y>580</y>
      <x>1032</x>
      <y>563</y>
      <x>1040</x>
      <y>556</y>
    </controlPt>
    <index>3</index>
    <review_code>C_v001</review_code>
  </line>
  <line>
    <name>Lane_White_Solid</name>
    <pose>Unspecified</pose>
    <truncated>0</truncated>
    <difficult>0</difficult>
    <controlPt>
      <x>1109</x>
      <y>548</y>
      <x>1096</x>
      <y>548</y>
      <x>1083</x>
      <y>554</y>
      <x>1091</x>
      <y>566</y>
      <x>1124</x>
      <y>581</y>
      <x>1147</x>
      <y>587</y>
      <x>1173</x>
      <y>595</y>
      <x>1680</x>
      <y>736</y>
    </controlPt>
    <index>5</index>
    <review_code>C_v001</review_code>
  </line>
</annotation>
