<?xml version="1.0" encoding="UTF-8"?>
<annotation>
  <ver>v001_1</ver>
  <folder>2</folder>
  <filename>2_20200731_141713_002790</filename>
  <path>Z:\freespace\IPIS_Freespace_verification\20200731_141713\ann</path>
  <source>
    <database>KATECH_DB</database>
  </source>
  <size>
    <width>1920</width>
    <height>1080</height>
    <depth>3</depth>
  </size>
  <segmented>0</segmented>
  <index_max>1</index_max>
 <polygon>
   <name>FreeSpace</name>
   <pose>Unspecified</pose>
   <truncated>0</truncated>
   <difficult>0</difficult>
   <PolyPt><x>469</x><y>758</y><x>821</x><y>610</y><x>945</x><y>562</y><x>961</x><y>560</y><x>972</x><y>560</y><x>977</x><y>560</y><x>984</x><y>560</y><x>986</x><y>560</y><x>992</x><y>560</y><x>1010</x><y>561</y><x>1016</x><y>562</y><x>1017</x><y>568</y><x>1028</x><y>568</y><x>1028</x><y>565</y><x>1031</x><y>564</y><x>1031</x><y>568</y><x>1034</x><y>568</y><x>1034</x><y>564</y><x>1041</x><y>564</y><x>1041</x><y>569</y><x>1057</x><y>569</y><x>1058</x><y>565</y><x>1059</x><y>563</y><x>1078</x><y>564</y><x>1097</x><y>567</y><x>1107</x><y>570</y><x>1106</x><y>585</y><x>1107</x><y>591</y><x>1110</x><y>597</y><x>1110</x><y>606</y><x>1112</x><y>615</y><x>1124</x><y>615</y><x>1126</x><y>607</y><x>1129</x><y>607</y><x>1131</x><y>608</y><x>1132</x><y>606</y><x>1133</x><y>610</y><x>1134</x><y>617</y><x>1136</x><y>623</y><x>1140</x><y>625</y><x>1148</x><y>626</y><x>1184</x><y>624</y><x>1199</x><y>615</y><x>1200</x><y>610</y><x>1204</x><y>609</y><x>1205</x><y>612</y><x>1209</x><y>610</y><x>1210</x><y>610</y><x>1211</x><y>620</y><x>1216</x><y>625</y><x>1229</x><y>625</y><x>1236</x><y>621</y><x>1237</x><y>608</y><x>1239</x><y>607</y><x>1240</x><y>602</y><x>1238</x><y>602</y><x>1238</x><y>595</y><x>1252</x><y>594</y><x>1254</x><y>593</y><x>1255</x><y>591</y><x>1288</x><y>594</y><x>1389</x><y>610</y><x>1442</x><y>622</y><x>1499</x><y>626</y><x>1549</x><y>632</y><x>1609</x><y>641</y><x>1712</x><y>657</y><x>1835</x><y>676</y><x>1888</x><y>691</y><x>1747</x><y>735</y><x>1532</x><y>762</y><x>1235</x><y>782</y><x>768</x><y>797</y><x>472</x><y>759</y>
   </PolyPt>
   <index>1</index>
   <review_code>C_v001</review_code>
 </polygon>
   </PolyPt>
   <index>2</index>
   <review_code>C_v001</review_code>
 </polygon>
</annotation>