<?xml version="1.0" encoding="UTF-8"?>
<annotation>
  <ver>v001_1</ver>
  <folder>2</folder>
  <filename>2_20200731_141713_000960</filename>
  <path>Z:\polygon\IPIS201201_verification\IPIS_4week_4d\20200731_141713\ann</path>
  <source>
    <database>KATECH_DB</database>
  </source>
  <size>
    <width>1920</width>
    <height>1080</height>
    <depth>3</depth>
  </size>
  <segmented>0</segmented>
  <index_max>3</index_max>
 <polygon>
   <name>Vehicle_Unknown</name>
   <pose>Unspecified</pose>
   <truncated>0</truncated>
   <difficult>0</difficult>
   <PolyPt><x>1129</x><y>541</y><x>1129</x><y>549</y><x>1129</x><y>554</y><x>1130</x><y>581</y><x>1131</x><y>589</y><x>1134</x><y>597</y><x>1135</x><y>607</y><x>1135</x><y>609</y><x>1137</x><y>611</y><x>1144</x><y>611</y><x>1149</x><y>607</y><x>1158</x><y>605</y><x>1161</x><y>608</y><x>1162</x><y>611</y><x>1163</x><y>619</y><x>1166</x><y>620</y><x>1174</x><y>621</y><x>1179</x><y>617</y><x>1182</x><y>612</y><x>1185</x><y>609</y><x>1191</x><y>608</y><x>1196</x><y>611</y><x>1213</x><y>612</y><x>1219</x><y>608</y><x>1227</x><y>609</y><x>1230</x><y>611</y><x>1230</x><y>616</y><x>1233</x><y>620</y><x>1238</x><y>621</y><x>1252</x><y>621</y><x>1255</x><y>613</y><x>1257</x><y>605</y><x>1257</x><y>592</y><x>1259</x><y>592</y><x>1264</x><y>593</y><x>1269</x><y>592</y><x>1274</x><y>591</y><x>1275</x><y>568</y><x>1275</x><y>562</y><x>1275</x><y>556</y><x>1270</x><y>557</y><x>1230</x><y>557</y><x>1227</x><y>554</y><x>1226</x><y>551</y><x>1226</x><y>543</y><x>1224</x><y>538</y><x>1223</x><y>533</y><x>1221</x><y>520</y><x>1214</x><y>514</y><x>1160</x><y>513</y><x>1145</x><y>522</y><x>1138</x><y>532</y><x>1136</x><y>538</y>
   </PolyPt>
   <index>1</index>
   <review_code>C_v001</review_code>
 </polygon>
 <polygon>
   <name>Vehicle_Unknown</name>
   <pose>Unspecified</pose>
   <truncated>0</truncated>
   <difficult>0</difficult>
   <PolyPt><x>1035</x><y>531</y><x>1032</x><y>531</y><x>1028</x><y>535</y><x>1025</x><y>539</y><x>1024</x><y>544</y><x>1024</x><y>564</y><x>1031</x><y>565</y><x>1034</x><y>562</y><x>1044</x><y>562</y><x>1049</x><y>565</y><x>1052</x><y>565</y><x>1053</x><y>563</y><x>1054</x><y>556</y><x>1052</x><y>539</y><x>1052</x><y>537</y><x>1050</x><y>534</y><x>1047</x><y>531</y><x>1044</x><y>530</y><x>1037</x><y>531</y>
   </PolyPt>
   <index>2</index>
   <review_code>C_v001</review_code>
 </polygon>
 <polygon>
   <name>Vehicle_Unknown</name>
   <pose>Unspecified</pose>
   <truncated>0</truncated>
   <difficult>0</difficult>
   <PolyPt><x>790</x><y>550</y><x>836</x><y>550</y><x>833</x><y>525</y><x>821</x><y>515</y><x>809</x><y>514</y><x>801</x><y>516</y><x>794</x><y>526</y><x>786</x><y>537</y><x>786</x><y>544</y>
   </PolyPt>
   <index>3</index>
   <review_code>C_v001</review_code>
 </polygon>
</annotation>