<?xml version="1.0" encoding="UTF-8"?>
<annotation>
  <ver>v001_1</ver>
  <folder>2</folder>
  <filename>2_20200731_141713_000270</filename>
  <path>Z:\polygon\IPIS201201_verification\IPIS_4week_4d\20200731_141713\ann</path>
  <source>
    <database>KATECH_DB</database>
  </source>
  <size>
    <width>1920</width>
    <height>1080</height>
    <depth>3</depth>
  </size>
  <segmented>0</segmented>
  <index_max>2</index_max>
 <polygon>
   <name>Vehicle_Unknown</name>
   <pose>Unspecified</pose>
   <truncated>0</truncated>
   <difficult>0</difficult>
   <PolyPt><x>992</x><y>543</y><x>991</x><y>549</y><x>992</x><y>558</y><x>993</x><y>563</y><x>997</x><y>563</y><x>997</x><y>561</y><x>1007</x><y>561</y><x>1009</x><y>562</y><x>1011</x><y>559</y><x>1011</x><y>552</y><x>1010</x><y>549</y><x>1008</x><y>543</y><x>999</x><y>542</y>
   </PolyPt>
   <index>1</index>
   <review_code>C_v001</review_code>
 </polygon>
 <polygon>
   <name>Vehicle_Unknown</name>
   <pose>Unspecified</pose>
   <truncated>0</truncated>
   <difficult>0</difficult>
   <PolyPt><x>818</x><y>524</y><x>805</x><y>529</y><x>800</x><y>534</y><x>797</x><y>540</y><x>796</x><y>543</y><x>797</x><y>552</y><x>836</x><y>551</y><x>842</x><y>551</y><x>841</x><y>543</y><x>842</x><y>535</y><x>840</x><y>530</y><x>839</x><y>526</y>
   </PolyPt>
   <index>2</index>
   <review_code>C_v001</review_code>
 </polygon>
</annotation>