<?xml version="1.0" encoding="UTF-8"?>
<annotation>
  <ver>v001_1</ver>
  <folder>2</folder>
  <filename>2_20200731_141713_000330</filename>
  <path>Z:\polygon\IPIS201201_verification\IPIS_4week_4d\20200731_141713\ann</path>
  <source>
    <database>KATECH_DB</database>
  </source>
  <size>
    <width>1920</width>
    <height>1080</height>
    <depth>3</depth>
  </size>
  <segmented>0</segmented>
  <index_max>3</index_max>
 <polygon>
   <name>Vehicle_Car</name>
   <pose>Unspecified</pose>
   <truncated>0</truncated>
   <difficult>0</difficult>
   <PolyPt><x>691</x><y>538</y><x>682</x><y>539</y><x>672</x><y>545</y><x>669</x><y>549</y><x>673</x><y>550</y><x>677</x><y>549</y><x>686</x><y>550</y><x>691</x><y>549</y><x>707</x><y>550</y><x>742</x><y>548</y><x>739</x><y>542</y><x>734</x><y>538</y><x>731</x><y>537</y>
   </PolyPt>
   <index>1</index>
   <review_code>C_v001</review_code>
 </polygon>
 <polygon>
   <name>Vehicle_Unknown</name>
   <pose>Unspecified</pose>
   <truncated>0</truncated>
   <difficult>0</difficult>
   <PolyPt><x>830</x><y>549</y><x>854</x><y>549</y><x>856</x><y>545</y><x>868</x><y>544</y><x>869</x><y>526</y><x>830</x><y>525</y>
   </PolyPt>
   <index>2</index>
   <review_code>C_v001</review_code>
 </polygon>
 <polygon>
   <name>Vehicle_Unknown</name>
   <pose>Unspecified</pose>
   <truncated>0</truncated>
   <difficult>0</difficult>
   <PolyPt><x>999</x><y>562</y><x>1018</x><y>563</y><x>1019</x><y>552</y><x>1017</x><y>543</y><x>1000</x><y>542</y>
   </PolyPt>
   <index>3</index>
   <review_code>C_v001</review_code>
 </polygon>
</annotation>